LICENSE
README.md
auri/__init__.py
auri/__main__.py
auri/ambilight.py
auri/ambilight_controller.py
auri/aurora.py
auri/command_line.py
auri/device_finder.py
auri/device_manager.py
auri/effects.py
pyproject.toml
auri-1.4.0.dist-info/entry_points.txt
auri-1.4.0.dist-info/LICENSE
auri-1.4.0.dist-info/WHEEL
auri-1.4.0.dist-info/METADATA
auri-1.4.0.dist-info/RECORD
