Metadata-Version: 2.1
Name: auri
Version: 1.4.0
Summary: CLI to control Nanoleaf Aurora devices
Home-page: https://github.com/MrTrustworthy/auri
License: MIT
Keywords: Aurora,Nanoleaf,cli,commandline
Author: MrTrustworthy
Author-email: tinywritingmakesmailhardtoread@gmail.com
Requires-Python: >=3.7,<4.0
Classifier: Development Status :: 4 - Beta
Classifier: License :: OSI Approved :: MIT License
Classifier: Programming Language :: Python :: 3
Classifier: Programming Language :: Python :: 3.7
Classifier: Programming Language :: Python :: 3.8
Classifier: Programming Language :: Python :: 3.9
Requires-Dist: click (>=7.0,<8.0)
Requires-Dist: jsonschema (>=3.2.0,<4.0.0)
Requires-Dist: pillow (>=7.0.0,<8.0.0)
Requires-Dist: psutil (>=5.6.7,<6.0.0)
Requires-Dist: requests (>=2.22.0,<3.0.0)
Project-URL: Repository, https://github.com/MrTrustworthy/auri
